setup.py
python_ses/__init__.py
python_ses.egg-info/PKG-INFO
python_ses.egg-info/SOURCES.txt
python_ses.egg-info/dependency_links.txt
python_ses.egg-info/not-zip-safe
python_ses.egg-info/requires.txt
python_ses.egg-info/top_level.txt