Metadata-Version: 1.1
Name: python-ses
Version: 0.3
Summary: Simple usefull lib to send email using AWS SES
Home-page: http://github.com/storborg/funniest
Author: Aaron Dominguez - Destacame Spa
Author-email: dominguezaaron75@gmail.com
License: MIT
Keywords: aws ses python email emailing
Platform: UNKNOWN
Classifier: Development Status :: 3 - Alpha
Classifier: License :: OSI Approved :: MIT License
Classifier: Programming Language :: Python :: 2.7
Classifier: Programming Language :: Python :: 3
Classifier: Topic :: Internet :: WWW/HTTP :: Dynamic Content
Classifier: Topic :: Software Development :: Libraries :: Python Modules
